Metadata-Version: 2.4
Name: adafruit-circuitpython-pixie
Version: 1.2.21
Summary: CircuitPython library for Pixie chainable 3W smart LED.
Author-email: Adafruit Industries <circuitpython@adafruit.com>
License: MIT
Project-URL: Homepage, https://github.com/adafruit/Adafruit_CircuitPython_Pixie
Keywords: adafruit,pixie,smart,led,breakout,hardware,micropython,circuitpython
Classifier: Intended Audience :: Developers
Classifier: Topic :: Software Development :: Libraries
Classifier: Topic :: Software Development :: Embedded Systems
Classifier: Topic :: System :: Hardware
Classifier: License :: OSI Approved :: MIT License
Classifier: Programming Language :: Python :: 3
License-File: LICENSE
Requires-Dist: Adafruit-Blinka
Requires-Dist: pyserial
Provides-Extra: optional
Dynamic: license-file
